bdfrrr/__init__.py
bdfrrr/__main__.py
bdfrrr/archiver.py
bdfrrr/cloner.py
bdfrrr/completion.py
bdfrrr/configuration.py
bdfrrr/connector.py
bdfrrr/default_config.cfg
bdfrrr/download_filter.py
bdfrrr/downloader.py
bdfrrr/exceptions.py
bdfrrr/file_name_formatter.py
bdfrrr/oauth2.py
bdfrrr/resource.py
bdfrrr/site_authenticator.py
bdfrrr/archive_entry/__init__.py
bdfrrr/archive_entry/base_archive_entry.py
bdfrrr/archive_entry/comment_archive_entry.py
bdfrrr/archive_entry/submission_archive_entry.py
bdfrrr/site_downloaders/__init__.py
bdfrrr/site_downloaders/base_downloader.py
bdfrrr/site_downloaders/delay_for_reddit.py
bdfrrr/site_downloaders/direct.py
bdfrrr/site_downloaders/download_factory.py
bdfrrr/site_downloaders/erome.py
bdfrrr/site_downloaders/gallery.py
bdfrrr/site_downloaders/gfycat.py
bdfrrr/site_downloaders/imgur.py
bdfrrr/site_downloaders/pornhub.py
bdfrrr/site_downloaders/redgifs.py
bdfrrr/site_downloaders/self_post.py
bdfrrr/site_downloaders/vidble.py
bdfrrr/site_downloaders/vreddit.py
bdfrrr/site_downloaders/youtube.py
bdfrrr/site_downloaders/fallback_downloaders/__init__.py
bdfrrr/site_downloaders/fallback_downloaders/fallback_downloader.py
bdfrrr/site_downloaders/fallback_downloaders/ytdlp_fallback.py
bdfrrr-2.6.2.data/data/config/default_config.cfg
bdfrrr-2.6.2.dist-info/LICENSE
bdfrrr-2.6.2.dist-info/METADATA
bdfrrr-2.6.2.dist-info/WHEEL
bdfrrr-2.6.2.dist-info/entry_points.txt
bdfrrr-2.6.2.dist-info/top_level.txt
bdfrrr-2.6.2.dist-info/RECORD
