Metadata-Version: 2.1
Name: bdfrrr
Version: 2.6.2
Summary: Downloads and archives content from reddit
Home-page: https://github.com/mattray0295/bdfrr
Author: Matt
Author-email: Ali Parlakci <parlakciali@gmail.com>
Maintainer-email: Serene Arc <serenical@gmail.com>
License: GNU GENERAL PUBLIC LICENSE
Project-URL: Homepage, https://aliparlakci.github.io/bulk-downloader-for-reddit
Project-URL: Source, https://github.com/aliparlakci/bulk-downloader-for-reddit
Project-URL: Bug Reports, https://github.com/aliparlakci/bulk-downloader-for-reddit/issues
Keywords: reddit,download,archive
Classifier: Development Status :: 5 - Production/Stable
Classifier: Environment :: Console
Classifier: License :: OSI Approved :: GNU General Public License v3 (GPLv3)
Classifier: Natural Language :: English
Classifier: Operating System :: OS Independent
Classifier: Programming Language :: Python :: 3
Classifier: Programming Language :: Python :: 3.9
Classifier: Programming Language :: Python :: 3.10
Classifier: Programming Language :: Python :: 3.11
Requires-Python: >=3.8
License-File: LICENSE
Requires-Dist: appdirs (>=1.4.4)
Requires-Dist: beautifulsoup4 (>=4.10.0)
Requires-Dist: click (>=8.0.0)
Requires-Dist: dict2xml (>=1.7.0)
Requires-Dist: praw (>=7.2.0)
Requires-Dist: pyyaml (>=5.4.1)
Requires-Dist: requests (>=2.25.1)
Requires-Dist: yt-dlp (>=2022.11.11)
Provides-Extra: dev
Requires-Dist: black (>=22.12.0) ; extra == 'dev'
Requires-Dist: Flake8-pyproject (>=1.2.2) ; extra == 'dev'
Requires-Dist: isort (>=5.11.4) ; extra == 'dev'
Requires-Dist: pre-commit (>=2.20.0) ; extra == 'dev'
Requires-Dist: pytest (>=7.1.0) ; extra == 'dev'
Requires-Dist: tox (>=3.27.1) ; extra == 'dev'
